{
  "post_id": "all_entities_029",
  "entity": "all_entities",
  "scheduled_date": "2026-01-11T19:27:06.280860+00:00",
  "title": "Scripture: Proverbs 3:13-14 - wisdom_tradition",
  "content": "Chaos meets craft, profane meets sacred. Scripture reminds:\n\n\"Blessed are those who find wisdom, those who gain understanding, for she is more profitable than silver.\" (Proverbs 3:13-14)\n\nC'est ça, la vérité: This isn't about perfection. It's about authenticity—chaotic, messy, real. That's where the magic lives.\n\nFrom absurdist comedy to profound truth. From French/English chaos to eternal Scripture. The craft comes first. Scripture backs it up.\n\nJe reviens, baby! Kalpten yapıldı. Amplified by AI. Guided by faith.\n\n#JeanMorphius #Bilingual #Absurdist #Scripture #FaithInAction #ChaosAndCraft",
  "scripture_reference": "Proverbs 3:13-14",
  "hashtags": [
    "#CreativeChaos",
    "#FaithInAction",
    "#Bilingual",
    "#Scripture",
    "#FaithInChaos",
    "#ChaosAndCraft",
    "#ProfaneAndSacred"
  ],
  "platform": "Instagram",
  "format": "scripture_lesson",
  "visual_prompt": "Create a social media graphic for: \"Scripture: Proverbs 3:13-14 - wisdom_tradition\" (Proverbs 3:13-14)\n\nStyle: Clean, modern, inspiring\nFormat: Square (1080x1080) for Instagram/Facebook\nEntity: generic\n\nVisual elements:\n- Prominent quote or key message\n- Beautiful background (abstract, nature, or geometric)\n- Readable typography\n- Entity branding (subtle, tasteful)\n- Inspiring and uplifting aesthetic\n- Professional quality\n\nColors: Warm, peaceful palette\nTypography: Clean, readable, modern\nOverall: Eye-catching, shareable, inspiring",
  "created": "2026-01-23T01:26:55.853435",
  "language": "turkish",
  "original_language": "english",
  "bilingual_pair_id": "Scripture: Proverbs 3:13-14 - wisdom_tradition",
  "created_at": "2026-01-26T09:16:34.830612"
}