{
  "post_id": "all_entities_160",
  "entity": "all_entities",
  "scheduled_date": "2026-03-03T09:12:06.468249+00:00",
  "title": "Scripture: Proverbs 14:23 - craft_work",
  "content": "Duygu Adamı. Emotion Man. The Word says:\n\n\"In all toil there is profit, but mere talk tends only to poverty.\" (Proverbs 14:23)\n\nHis önce. Feeling first. This is sound architecture. Built on feeling. Driven by emotion. That's where the truth lives.\n\nFrom Turkish heart to English soul. From feeling to sound. From emotion to Scripture. Duygu Adamı. Emotion Man. The craft comes first. Scripture backs it up.\n\nKalpten yapıldı. Amplified by AI. Guided by faith.\n\n#Karasahin #DuyguAdami #EmotionMan #Scripture #FaithInAction #SoundArchitecture",
  "scripture_reference": "Proverbs 14:23",
  "hashtags": [
    "#Scripture",
    "#SonicStoryteller",
    "#VoiceOfGod",
    "#Karasahin",
    "#EmotionFirst",
    "#DuyguAdami",
    "#SoundArchitecture"
  ],
  "platform": "LinkedIn",
  "format": "scripture_lesson",
  "visual_prompt": "Create a social media graphic for: \"Scripture: Proverbs 14:23 - craft_work\" (Proverbs 14:23)\n\nStyle: Clean, modern, inspiring\nFormat: Square (1080x1080) for Instagram/Facebook\nEntity: generic\n\nVisual elements:\n- Prominent quote or key message\n- Beautiful background (abstract, nature, or geometric)\n- Readable typography\n- Entity branding (subtle, tasteful)\n- Inspiring and uplifting aesthetic\n- Professional quality\n\nColors: Warm, peaceful palette\nTypography: Clean, readable, modern\nOverall: Eye-catching, shareable, inspiring",
  "created": "2026-01-23T01:26:56.043187",
  "language": "turkish",
  "original_language": "english",
  "bilingual_pair_id": "Scripture: Proverbs 14:23 - craft_work",
  "created_at": "2026-01-26T09:16:35.092686"
}